radonpy/__init__.py
radonpy/core/__init__.py
radonpy/core/calc.py
radonpy/core/const.py
radonpy/core/poly.py
radonpy/core/utils.py
radonpy/ff/__init__.py
radonpy/ff/descriptor.py
radonpy/ff/ff_class.py
radonpy/ff/gaff.py
radonpy/ff/gaff2.py
radonpy/ff/gaff2_mod.py
radonpy/ff/ff_dat/gaff.json
radonpy/ff/ff_dat/gaff2.json
radonpy/ff/ff_dat/gaff2_mod.json
radonpy/sim/__init__.py
radonpy/sim/helper.py
radonpy/sim/lammps.py
radonpy/sim/md.py
radonpy/sim/md_wrapper.py
radonpy/sim/psi4_wrapper.py
radonpy/sim/qm.py
radonpy/sim/qm_wrapper.py
radonpy/sim/preset/__init__.py
radonpy/sim/preset/eq.py
radonpy/sim/preset/tc.py
radonpy_pypi-0.2.11.dist-info/LICENSE
radonpy_pypi-0.2.11.dist-info/METADATA
radonpy_pypi-0.2.11.dist-info/WHEEL
radonpy_pypi-0.2.11.dist-info/top_level.txt
radonpy_pypi-0.2.11.dist-info/RECORD
