Metadata-Version: 2.1
Name: radonpy-pypi
Version: 0.2.11
Summary: RadonPy is a Python library to automate physical property calculations for polymer informatics.
Home-page: https://github.com/RadonPy/RadonPy
Author: Yoshihiro Hayashi
Author-email: yhayashi@ism.ac.jp
License: BSD-3-Clause
Keywords: polymer informatics,molecular dynamics
Platform: Linux
Platform: Mac OS-X
Platform: Unix
Platform: Windows
Classifier: Development Status :: 5 - Production/Stable
Classifier: License :: OSI Approved :: BSD License
Classifier: Programming Language :: Python
Classifier: Programming Language :: Python :: 3
Classifier: Programming Language :: Python :: 3.7
Classifier: Programming Language :: Python :: 3.8
Classifier: Programming Language :: Python :: 3.9
Classifier: Programming Language :: Python :: 3.10
Classifier: Programming Language :: Python :: 3.11
Classifier: Topic :: Scientific/Engineering :: Chemistry
Classifier: Topic :: Scientific/Engineering :: Physics
Classifier: Topic :: Software Development :: Libraries :: Python Modules
Requires-Python: >=3.7
License-File: LICENSE
Requires-Dist: numpy
Requires-Dist: pandas
Requires-Dist: scipy
Requires-Dist: psutil
Requires-Dist: matplotlib
Requires-Dist: rdkit (>=2020.03)
Requires-Dist: mdtraj (>=1.9)
Provides-Extra: lammps
Requires-Dist: lammps (>=2020.03.03) ; extra == 'lammps'
